{
	"backtrace" : 0,
	"backtraceGraph" : 
	{
		"commands" : [],
		"files" : 
		[
			"CmdManager/CMakeLists.txt"
		],
		"nodes" : 
		[
			{
				"file" : 0
			}
		]
	},
	"dependencies" : 
	[
		{
			"id" : "CmdManagerLib_autogen_timestamp_deps::@93d986cb355c2d8c58ff"
		}
	],
	"id" : "CmdManagerLib_autogen::@93d986cb355c2d8c58ff",
	"isGeneratorProvided" : true,
	"name" : "CmdManagerLib_autogen",
	"paths" : 
	{
		"build" : "CmdManager",
		"source" : "CmdManager"
	},
	"sourceGroups" : 
	[
		{
			"name" : "",
			"sourceIndexes" : 
			[
				0
			]
		},
		{
			"name" : "CMake Rules",
			"sourceIndexes" : 
			[
				1,
				2
			]
		}
	],
	"sources" : 
	[
		{
			"backtrace" : 0,
			"isGenerated" : true,
			"path" : "cmake-build-debug/CmdManager/CMakeFiles/CmdManagerLib_autogen",
			"sourceGroupIndex" : 0
		},
		{
			"backtrace" : 0,
			"isGenerated" : true,
			"path" : "cmake-build-debug/CmdManager/CMakeFiles/CmdManagerLib_autogen.rule",
			"sourceGroupIndex" : 1
		},
		{
			"backtrace" : 0,
			"isGenerated" : true,
			"path" : "cmake-build-debug/CmdManager/CmdManagerLib_autogen/timestamp.rule",
			"sourceGroupIndex" : 1
		}
	],
	"type" : "UTILITY"
}
